{
  "type": "buntsy:grinding_wheel",
  "ingredients": [
    {
      "item": "minecraft:redstone_ore"
    },
    {
      "item": "minecraft:deepslate_redstone_ore"
    }
  ],
  "output": [
    {
      "count": 6,
      "chance": 1.0,
      "item": "minecraft:redstone"
    },
    {
      "count": 1,
      "chance": 0.5,
      "item": "minecraft:redstone"
    },
    {
      "count": 1,
      "chance": 0.25,
      "item": "minecraft:redstone"
    },
    {
      "count": 1,
      "chance": 0.1,
      "item": "buntsy:pristine_redstone_sample"
    }
  ]
}