{
  "parent": "minecraft:recipes/root",
  "criteria": {
    "has_moth_wing_thread": {
      "conditions": {
        "items": [
          {
            "items": [
              "buntsy:moth_wing_thread"
            ]
          }
        ]
      },
      "trigger": "minecraft:inventory_changed"
    },
    "has_silk_fabric": {
      "conditions": {
        "items": [
          {
            "items": [
              "buntsy:silk_fabric"
            ]
          }
        ]
      },
      "trigger": "minecraft:inventory_changed"
    },
    "has_the_recipe": {
      "conditions": {
        "recipe": "buntsy:tough_silk_fabric"
      },
      "trigger": "minecraft:recipe_unlocked"
    }
  },
  "requirements": [
    [
      "has_silk_fabric",
      "has_moth_wing_thread",
      "has_the_recipe"
    ]
  ],
  "rewards": {
    "recipes": [
      "buntsy:tough_silk_fabric"
    ]
  },
  "sends_telemetry_event": false
}